backpack/__init__.py
backpack/backpack.py
backpack/cli.py
backpack/logger.py
backpack/utils.py
backpack_backup-0.0.3.post1.dist-info/LICENSE
backpack_backup-0.0.3.post1.dist-info/METADATA
backpack_backup-0.0.3.post1.dist-info/WHEEL
backpack_backup-0.0.3.post1.dist-info/entry_points.txt
backpack_backup-0.0.3.post1.dist-info/top_level.txt
backpack_backup-0.0.3.post1.dist-info/RECORD
