Metadata-Version: 2.1
Name: backpack-backup
Version: 0.0.3.post1
Summary: A tool to sign, encrypt and, backup a file or directory using GPG.
Home-page: http://gitlab.com/unkwn1/backpack-backup
Author: unkwn1
Author-email: unkwn1@tutanota.com
License: GPLv3
Project-URL: Issues, https://gitlab.com/unkwn1/backpack-backup/-/issues
Project-URL: Source, https://gitlab.com/unkwn1/backpack-backup/-/tree/main
Platform: UNKNOWN
Classifier: Development Status :: 3 - Alpha
Classifier: Programming Language :: Python :: 3.9
Classifier: Programming Language :: Python :: 3.10
Classifier: Topic :: Software Development :: Libraries :: Python Modules
License-File: LICENSE
Requires-Dist: python-gnupg (==0.4.8)
Requires-Dist: termcolor (==1.1.0)
